l0n0lvedio2image/__init__.py
l0n0lvedio2image/img_to_vedio.py
l0n0lvedio2image/vedio_to_img.py
l0n0lvedio2image-1.0.4.dist-info/LICENSE
l0n0lvedio2image-1.0.4.dist-info/METADATA
l0n0lvedio2image-1.0.4.dist-info/WHEEL
l0n0lvedio2image-1.0.4.dist-info/entry_points.txt
l0n0lvedio2image-1.0.4.dist-info/top_level.txt
l0n0lvedio2image-1.0.4.dist-info/RECORD
