Metadata-Version: 2.1
Name: l0n0lvedio2image
Version: 1.0.4
Summary: 视频与png图片之间的转换
Home-page: https://gitee.com/l00n00l/l0n0lvedio2image.git
Author: l0n0l
Author-email: 1038352856@qq.com
Classifier: Programming Language :: Python :: 3
Classifier: License :: OSI Approved :: MIT License
Classifier: Operating System :: OS Independent
Requires-Python: >=3.9
License-File: LICENSE
Requires-Dist: opencv-python
